datalakesurfer/__init__.py
datalakesurfer/fabric_format_detector.py
datalakesurfer/format_detector.py
datalakesurfer/gcs_format_detector.py
datalakesurfer/s3_format_detector.py
datalakesurfer/detectors/__init__.py
datalakesurfer/detectors/base_detector.py
datalakesurfer/detectors/delta_detector.py
datalakesurfer/detectors/fabric_delta_detector.py
datalakesurfer/detectors/fabric_iceberg_detector.py
datalakesurfer/detectors/fabric_parquet_detector.py
datalakesurfer/detectors/gcs_base_detector.py
datalakesurfer/detectors/gcs_delta_detector.py
datalakesurfer/detectors/gcs_iceberg_detector.py
datalakesurfer/detectors/gcs_parquet_detector.py
datalakesurfer/detectors/iceberg_detector.py
datalakesurfer/detectors/parquet_detector.py
datalakesurfer/detectors/s3_base_detector.py
datalakesurfer/detectors/s3_delta_detector.py
datalakesurfer/detectors/s3_iceberg_detector.py
datalakesurfer/detectors/s3_parquet_detector.py
datalakesurfer/models/__init__.py
datalakesurfer/models/adls_models.py
datalakesurfer/models/fabric_models.py
datalakesurfer/models/gcs_models.py
datalakesurfer/models/s3_models.py
datalakesurfer/query/__init__.py
datalakesurfer/query/adls_delta_query.py
datalakesurfer/query/adls_iceberg_query.py
datalakesurfer/query/adls_parquet_query.py
datalakesurfer/query/base_query.py
datalakesurfer/query/fabric_delta_query.py
datalakesurfer/query/fabric_iceberg_query.py
datalakesurfer/query/fabric_parquet_query.py
datalakesurfer/query/gcs_delta_query.py
datalakesurfer/query/gcs_iceberg_query.py
datalakesurfer/query/gcs_parquet_query.py
datalakesurfer/query/s3_delta_query.py
datalakesurfer/query/s3_iceberg_query.py
datalakesurfer/query/s3_parquet_query.py
datalakesurfer/schemas/__init__.py
datalakesurfer/schemas/base_schema.py
datalakesurfer/schemas/delta_schema.py
datalakesurfer/schemas/fabric_delta_schema.py
datalakesurfer/schemas/fabric_iceberg_schema.py
datalakesurfer/schemas/fabric_parquet_schema.py
datalakesurfer/schemas/gcs_delta_schema.py
datalakesurfer-0.1.6.dist-info/LICENSE
datalakesurfer-0.1.6.dist-info/METADATA
datalakesurfer-0.1.6.dist-info/WHEEL
datalakesurfer-0.1.6.dist-info/top_level.txt
datalakesurfer-0.1.6.dist-info/RECORD
