Metadata-Version: 2.1
Name: datalakesurfer
Version: 0.1.6
Summary: A Python package for Azure Datalake Storage adlsgen2 [abfss://] and Microsoft Fabric Lakehouse [abfss://], Google Cloud Storage [gs://bucket], AWS S3 bucket [s3://bucket] enables format detection and schema retrieval for Iceberg, Delta, and Parquet formats.It helps identify paritioned columns for parquet datasets. It also supports querying Delta, Parquet, and Iceberg formats through SQL constructs.
Home-page: https://github.com/keshavksingh/datalakesurfer
Author: Keshav Kant Singh
Author-email: masterkeshav@gmail.com
Classifier: Programming Language :: Python :: 3
Classifier: License :: OSI Approved :: MIT License
Classifier: Operating System :: OS Independent
Requires-Python: >=3.8
License-File: LICENSE
Requires-Dist: pyarrowfs-adlgen2==0.2.5
Requires-Dist: adlfs==2024.12.0
Requires-Dist: python-dotenv==1.0.1
Requires-Dist: azure-identity==1.17.1
Requires-Dist: azure-storage-file-datalake==12.21.0
Requires-Dist: numpy==1.26.4
Requires-Dist: pandas==1.5.3
Requires-Dist: pytest==8.3.3
Requires-Dist: pyOpenSSL==24.2.1
Requires-Dist: cryptography==43.0.1
Requires-Dist: duckdb==1.3.2
Requires-Dist: deltalake==1.1.4
Requires-Dist: pydantic==2.11.7
Requires-Dist: gcsfs==2025.7.0
Requires-Dist: s3fs==2025.7.0
